MANIFEST.in
NEWS.txt
README.rst
setup.py
src/django_fsfield.egg-info/PKG-INFO
src/django_fsfield.egg-info/SOURCES.txt
src/django_fsfield.egg-info/dependency_links.txt
src/django_fsfield.egg-info/not-zip-safe
src/django_fsfield.egg-info/top_level.txt
src/fsfield/__init__.py
src/fsfield/core.py
src/fsfield/fields.py
src/fsfield/models.py
src/fsfield/settings.py
src/fsfield/views.py
src/fsfield/tests/__init__.py
src/fsfield/tests/base.py
src/fsfield/tests/models.py
src/fsfield/tests/test_core.py
src/fsfield/tests/test_fields.py