Metadata-Version: 1.0
Name: django-fsfield
Version: 0.5.3
Summary: Scalabe file storage fields for your Django models
Home-page: UNKNOWN
Author: Luper Rouch
Author-email: luper.rouch@gmail.com
License: BSD License
Keywords: django file storage models
Platform: UNKNOWN
